{
  "db_name": "PostgreSQL",
  "query": "SELECT scryfall_data_id, is_token, mechanical_categories, oracle_tags, oracle_tags_by_role, other_oracle_tags, created_at, updated_at\n            FROM card_profiles WHERE scryfall_data_id = ANY($1)",
  "describe": {
    "columns": [
      {
        "ordinal": 0,
        "name": "scryfall_data_id",
        "type_info": "Uuid"
      },
      {
        "ordinal": 1,
        "name": "is_token",
        "type_info": "Bool"
      },
      {
        "ordinal": 2,
        "name": "mechanical_categories",
        "type_info": "Jsonb"
      },
      {
        "ordinal": 3,
        "name": "oracle_tags",
        "type_info": "Jsonb"
      },
      {
        "ordinal": 4,
        "name": "oracle_tags_by_role",
        "type_info": "Jsonb"
      },
      {
        "ordinal": 5,
        "name": "other_oracle_tags",
        "type_info": "Jsonb"
      },
      {
        "ordinal": 6,
        "name": "created_at",
        "type_info": "Timestamptz"
      },
      {
        "ordinal": 7,
        "name": "updated_at",
        "type_info": "Timestamptz"
      }
    ],
    "parameters": {
      "Left": [
        "UuidArray"
      ]
    },
    "nullable": [
      false,
      false,
      true,
      false,
      false,
      false,
      false,
      false
    ]
  },
  "hash": "89eb070d6df3776cbdfb05f5d5da652af95e9e895eaaeae3634a719ff0c6535d"
}
