{
  "db_name": "PostgreSQL",
  "query": "SELECT scryfall_data_id, is_token, mechanical_categories, oracle_tags, created_at, updated_at FROM card_profiles WHERE scryfall_data_id = $1",
  "describe": {
    "columns": [
      {
        "ordinal": 0,
        "name": "scryfall_data_id",
        "type_info": "Uuid"
      },
      {
        "ordinal": 1,
        "name": "is_token",
        "type_info": "Bool"
      },
      {
        "ordinal": 2,
        "name": "mechanical_categories",
        "type_info": "Jsonb"
      },
      {
        "ordinal": 3,
        "name": "oracle_tags",
        "type_info": "Jsonb"
      },
      {
        "ordinal": 4,
        "name": "created_at",
        "type_info": "Timestamptz"
      },
      {
        "ordinal": 5,
        "name": "updated_at",
        "type_info": "Timestamptz"
      }
    ],
    "parameters": {
      "Left": [
        "Uuid"
      ]
    },
    "nullable": [
      false,
      false,
      true,
      false,
      false,
      false
    ]
  },
  "hash": "05465c6eb0de31a45c8a9fc43b9e2085b1a409bb66f9b7c849a11fa098bfc433"
}
